syslogformat/__init__.py
syslogformat/exceptions.py
syslogformat/facility.py
syslogformat/formatter.py
syslogformat/helpers.py
syslogformat/py.typed
syslogformat/severity.py
syslogformat/types.py
syslogformat-1.0.0.dist-info/LICENSE
syslogformat-1.0.0.dist-info/METADATA
syslogformat-1.0.0.dist-info/WHEEL
syslogformat-1.0.0.dist-info/top_level.txt
syslogformat-1.0.0.dist-info/RECORD
