Metadata-Version: 2.1
Name: syslogformat
Version: 1.0.0
Summary: Python `logging.Formatter` class for syslog style messages
Author-email: Daniil Fajnberg <mail@daniil.fajnberg.de>
Maintainer-email: Daniil Fajnberg <mail@daniil.fajnberg.de>
License: Apache Software License Version 2.0
Project-URL: Repository, https://github.com/daniil-berg/syslogformat
Project-URL: Issue Tracker, https://github.com/daniil-berg/syslogformat/issues
Project-URL: Documentation, http://daniil-berg.github.io/syslogformat
Keywords: logging,formatting,syslog
Classifier: Development Status :: 4 - Beta
Classifier: Programming Language :: Python :: 3 :: Only
Classifier: Programming Language :: Python :: 3.8
Classifier: Programming Language :: Python :: 3.9
Classifier: Programming Language :: Python :: 3.10
Classifier: Programming Language :: Python :: 3.11
Classifier: Programming Language :: Python :: 3.12
Classifier: Operating System :: OS Independent
Classifier: License :: OSI Approved :: Apache Software License
Classifier: Intended Audience :: Developers
Classifier: Topic :: System :: Logging
Requires-Python: <4.0,>=3.8
License-File: LICENSE
Provides-Extra: dev
Requires-Dist: black ==23.11.0 ; extra == 'dev'
Requires-Dist: build ==1.0.3 ; extra == 'dev'
Requires-Dist: coverage[toml] ==7.3.2 ; extra == 'dev'
Requires-Dist: isort ==5.12.0 ; extra == 'dev'
Requires-Dist: mkdocs-material ==9.4.8 ; extra == 'dev'
Requires-Dist: mkdocstrings[python] ==0.24.0 ; extra == 'dev'
Requires-Dist: mypy ==1.7.0 ; extra == 'dev'
Requires-Dist: pytest ==7.4.3 ; extra == 'dev'
Requires-Dist: ruff ==0.1.5 ; extra == 'dev'
Provides-Extra: full
